clever_chat/__init__.py
clever_chat/client.py
clever_chat/errors.py
clever_chat/result.py
cleverchat.py-0.0.3.dist-info/LICENSE
cleverchat.py-0.0.3.dist-info/METADATA
cleverchat.py-0.0.3.dist-info/WHEEL
cleverchat.py-0.0.3.dist-info/top_level.txt
cleverchat.py-0.0.3.dist-info/RECORD
