Metadata-Version: 2.1
Name: cleverchat.py
Version: 0.0.3
Summary: API Wrapper for clever-chat API
Home-page: https://github.com/Hype3808/CleverChat.py
Author: Hype3808
License: MIT
Keywords: chatbot,clever-chat,clever-bot,chat,bot
Platform: UNKNOWN
Classifier: Development Status :: 3 - Alpha
Classifier: Intended Audience :: Developers
Classifier: License :: OSI Approved :: MIT License
Classifier: Programming Language :: Python :: 3
Requires-Python: >=3.4
License-File: LICENSE
Requires-Dist: aiohttp
Requires-Dist: requests
